README.rst
setup.cfg
setup.py
lyricsfinder/__info__.py
lyricsfinder/__init__.py
lyricsfinder/__main__.py
lyricsfinder/extractor.py
lyricsfinder/manager.py
lyricsfinder/utils.py
lyricsfinder.egg-info/PKG-INFO
lyricsfinder.egg-info/SOURCES.txt
lyricsfinder.egg-info/dependency_links.txt
lyricsfinder.egg-info/entry_points.txt
lyricsfinder.egg-info/requires.txt
lyricsfinder.egg-info/top_level.txt
lyricsfinder.egg-info/zip-safe
lyricsfinder/extractors/__init__.py
lyricsfinder/extractors/animelyrics.py
lyricsfinder/extractors/azlyrics.py
lyricsfinder/extractors/genius.py
lyricsfinder/extractors/lyrical_nonsense.py
lyricsfinder/extractors/lyricsmode.py
lyricsfinder/extractors/musixmatch.py
lyricsfinder/models/__init__.py
lyricsfinder/models/exceptions.py
lyricsfinder/models/lyrics.py
lyricsfinder/models/result.py