Metadata-Version: 2.1
Name: lyricsfinder
Version: 2.1.0
Summary: Retrieve lyrics from various websites
Home-page: https://github.com/GieselaDev/LyricsFinder
Author: siku2
Author-email: siku2@giesela.org
License: MIT License
